CHANGELOG.rst
MANIFEST.in
README.rst
buildout.cfg
setup.py
bobtemplates/__init__.py
bobtemplates/__init__.pyc
bobtemplates.niteoweb.egg-info/PKG-INFO
bobtemplates.niteoweb.egg-info/SOURCES.txt
bobtemplates.niteoweb.egg-info/dependency_links.txt
bobtemplates.niteoweb.egg-info/namespace_packages.txt
bobtemplates.niteoweb.egg-info/not-zip-safe
bobtemplates.niteoweb.egg-info/requires.txt
bobtemplates.niteoweb.egg-info/top_level.txt
bobtemplates/plone/.gitignore
bobtemplates/plone/.mrbob.ini
bobtemplates/plone/.travis.yml.bob
bobtemplates/plone/MANIFEST.in.bob
bobtemplates/plone/Makefile.bob
bobtemplates/plone/README.rst.bob
bobtemplates/plone/bootstrap.py
bobtemplates/plone/buildout.cfg
bobtemplates/plone/setup.py.bob
bobtemplates/plone/buildout.d/base.cfg.bob
bobtemplates/plone/buildout.d/development.cfg.bob
bobtemplates/plone/buildout.d/travis.cfg
bobtemplates/plone/buildout.d/versions.cfg.bob
bobtemplates/plone/docs/CHANGELOG.rst.bob
bobtemplates/plone/docs/LICENSE.rst.bob
bobtemplates/plone/docs/api.rst.bob
bobtemplates/plone/docs/conf.py.bob
bobtemplates/plone/docs/glossary.rst.bob
bobtemplates/plone/docs/index.rst.bob
bobtemplates/plone/docs/_static/.gitkeep
bobtemplates/plone/src/+package.namespace+/__init__.py
bobtemplates/plone/src/+package.namespace+/+package.name+/__init__.py.bob
bobtemplates/plone/src/+package.namespace+/+package.name+/configure.zcml.bob
bobtemplates/plone/src/+package.namespace+/+package.name+/interfaces.py.bob
bobtemplates/plone/src/+package.namespace+/+package.name+/testing.py.bob
bobtemplates/plone/src/+package.namespace+/+package.name+/browser/__init__.py
bobtemplates/plone/src/+package.namespace+/+package.name+/browser/configure.zcml.bob
bobtemplates/plone/src/+package.namespace+/+package.name+/browser/overrides/.gitkeep
bobtemplates/plone/src/+package.namespace+/+package.name+/browser/static/.gitkeep
bobtemplates/plone/src/+package.namespace+/+package.name+/profiles/default/browserlayer.xml.bob
bobtemplates/plone/src/+package.namespace+/+package.name+/profiles/default/metadata.xml
bobtemplates/plone/src/+package.namespace+/+package.name+/tests/__init__.py
bobtemplates/plone/src/+package.namespace+/+package.name+/tests/test_setup.py.bob
bobtemplates/pyramid/.coveralls.yml
bobtemplates/pyramid/.gitignore.bob
bobtemplates/pyramid/.mrbob.ini
