Metadata-Version: 1.1
Name: bobtemplates.niteoweb
Version: 0.3
Summary: Templates for NiteoWeb projects.
Home-page: https://github.com/niteoweb/bobtemplates.niteoweb
Author: NiteoWeb Ltd.
Author-email: info@niteoweb.com
License: BSD
Platform: UNKNOWN
Classifier: Environment :: Console
Classifier: Intended Audience :: Developers
Classifier: License :: OSI Approved :: BSD License
Classifier: Natural Language :: English
Classifier: Operating System :: OS Independent
Classifier: Programming Language :: Python
Classifier: Topic :: Software Development :: Code Generators
Classifier: Topic :: Utilities
